{
  "url": "https://quotes.toscrape.com/author/J-D-Salinger",
  "title": "Quotes to Scrape",
  "chunk_id": "00074_dba9c1dd.json_1",
  "text": "Hamilton and the release in the late 1990s of memoirs written by two people close to him: Joyce Maynard, an ex-lover; and Margaret Salinger, his daughter. In 1996, a small publisher announced a deal with Salinger to publish \"Hapworth 16, 1924\" in book form, but amid the ensuing publicity, the release was indefinitely delayed. He made headlines around the globe in June 2009, after filing a lawsuit against another writer for copyright infringement resulting from that writer's use of one of Salinger's characters from The Catcher in the Rye. Salinger died of natural causes on January 27, 2010, at his home in Cornish, New Hampshire.",
  "source_file": "00074_dba9c1dd.json"
}